apistar_ponyorm/__init__.py
apistar_ponyorm/apistar_ponyorm.py
apistar_ponyorm-0.2.8.dist-info/METADATA
apistar_ponyorm-0.2.8.dist-info/RECORD
apistar_ponyorm-0.2.8.dist-info/WHEEL
apistar_ponyorm-0.2.8.dist-info/dependency_links.txt
apistar_ponyorm-0.2.8.dist-info/pbr.json
apistar_ponyorm-0.2.8.dist-info/top_level.txt
