Metadata-Version: 2.1
Name: apistar-ponyorm
Version: 0.2.8
Summary: Third-party for apistar using pony orm
Home-page: https://github.com/jgirardet/apistar_ponyorm
Author: Jimmy Girardet
Author-email: ijkl@netc.fr
License: UNKNOWN
Platform: UNKNOWN
Classifier: Intended Audience :: System Administrators
Classifier: License :: OSI Approved :: GNU General Public License v3 or later (GPLv3+)
Classifier: Operating System :: POSIX :: Linux
Classifier: Programming Language :: Python
Classifier: Programming Language :: Python :: 3.6
Requires-Dist: pony
Requires-Dist: apistar
Requires-Dist: pbr (>=3.0)
